{"version":1,"date":"2026-07-03","seed":"2026-07-03#37","archetype":"kicker","map":{"id":"gen-2026-07-03#37","spawn":{"x":1019.5112813949584,"y":40},"ballRadius":10,"surfaces":[{"id":"wall-left","a":{"x":12,"y":0},"b":{"x":12,"y":640},"restitution":0.4,"friction":0.1,"kind":"wall"},{"id":"wall-right","a":{"x":1268,"y":0},"b":{"x":1268,"y":640},"restitution":0.4,"friction":0.1,"kind":"wall"},{"id":"floor","a":{"x":0,"y":632},"b":{"x":1280,"y":632},"restitution":0.15,"friction":0.9,"kind":"basin"},{"id":"ramp-0","a":{"x":1059.5112813949584,"y":100.553730847314},"b":{"x":558.8227574467658,"y":200.14555096177634},"restitution":0.25,"friction":0.3,"kind":"ramp"},{"id":"ramp-1","a":{"x":287.4629864933347,"y":250.0993516521367},"b":{"x":734.3430951478338,"y":334.2074609572713},"restitution":0.2,"friction":0.5,"kind":"conveyor","belt":248.55144146829844},{"id":"ramp-2","a":{"x":967.957976413479,"y":387.42363222517935},"b":{"x":452.13212620090496,"y":496.0351548786611},"restitution":0.2,"friction":0.5,"kind":"conveyor","belt":327.2794190235436},{"id":"ramp-return","a":{"x":442.5367117019424,"y":616},"b":{"x":404.13212620090496,"y":609.0409997662458},"restitution":0.25,"friction":0.3,"kind":"ramp"},{"id":"basin-lip-far","a":{"x":681.0293945612339,"y":632},"b":{"x":681.0293945612339,"y":560},"restitution":0.3,"friction":0.2,"kind":"lip"},{"id":"basin-curb-near","a":{"x":352.88549850116937,"y":632},"b":{"x":352.88549850116937,"y":618},"restitution":0.3,"friction":0.2,"kind":"lip"}],"bumpers":[{"id":"bumper-kick","pos":{"x":364.13212620090496,"y":569.0409997662458},"radius":26,"kick":914.868365614675,"maxHits":3}],"pads":[{"id":"pad-boost","pos":{"x":787.4298332950209,"y":154.67337877128995},"radius":22,"push":{"x":-234.96757986953236,"y":46.73733834074929}}]},"landing":{"x":461.9018845772966,"y":622},"digest":"00de2e81b06875ea","ticks":1341,"parPx":20,"funScore":12.3625}